turingquant/__init__.py
turingquant/benchmark.py
turingquant/metrics.py
turingquant/optimizers.py
turingquant/plot_metrics.py
turingquant/support.py
turingquant-0.2.2.dist-info/LICENSE
turingquant-0.2.2.dist-info/METADATA
turingquant-0.2.2.dist-info/WHEEL
turingquant-0.2.2.dist-info/top_level.txt
turingquant-0.2.2.dist-info/RECORD
