Metadata-Version: 2.1
Name: turingquant
Version: 0.2.2
Summary: Ferramentas para obtenção e manipulação de dados financeiros.
Home-page: https://grupoturing.com.br
Author: Grupo Turing
Author-email: turing.usp@gmail.com
License: UNKNOWN
Project-URL: Source Code, https://github.com/GrupoTuring/turingquant
Keywords: quant data scraping quantitative finance benchmark backtest
Platform: UNKNOWN
Classifier: Programming Language :: Python :: 3
Classifier: License :: OSI Approved :: MIT License
Classifier: Operating System :: OS Independent
Requires-Python: >=3.6
